transcribe_me/__init__.py
transcribe_me/cli.py
transcribe_me/main.py
transcribe_me/audio/__init__.py
transcribe_me/audio/splitting.py
transcribe_me/audio/transcription.py
transcribe_me/config/__init__.py
transcribe_me/config/config_manager.py
transcribe_me/config/schema.yaml
transcribe_me-1.0.1.dist-info/licenses/LICENSE
transcribe_me-1.0.1.dist-info/METADATA
transcribe_me-1.0.1.dist-info/WHEEL
transcribe_me-1.0.1.dist-info/entry_points.txt
transcribe_me-1.0.1.dist-info/top_level.txt
transcribe_me-1.0.1.dist-info/RECORD
