Metadata-Version: 2.4
Name: transcribe-me
Version: 1.0.1
Summary: A CLI tool to transcribe audio files using OpenAI API
Author-email: echoHello <bash@echohello.dev>
License-Expression: MIT
Project-URL: Homepage, https://github.com/echohello-dev/transcribe-me
Project-URL: Bug Tracker, https://github.com/echohello-dev/transcribe-me/issues
Classifier: Programming Language :: Python :: 3
Classifier: Operating System :: OS Independent
Requires-Python: >=3.12
License-File: LICENSE
Requires-Dist: pydub
Requires-Dist: tqdm
Requires-Dist: pyyaml
Requires-Dist: colorama
Requires-Dist: halo
Requires-Dist: yamale
Requires-Dist: tenacity>=0.20.0
Provides-Extra: openai
Requires-Dist: openai>=1.0.0; extra == "openai"
Provides-Extra: assemblyai
Requires-Dist: assemblyai>=0.16.0; extra == "assemblyai"
Provides-Extra: all
Requires-Dist: openai>=1.0.0; extra == "all"
Requires-Dist: assemblyai>=0.16.0; extra == "all"
Provides-Extra: test
Requires-Dist: pytest>=7.0.0; extra == "test"
Requires-Dist: pytest-cov>=4.0.0; extra == "test"
Requires-Dist: pytest-mock>=3.10.0; extra == "test"
Requires-Dist: pytest-xdist>=3.0.0; extra == "test"
Requires-Dist: coverage[toml]>=6.0.0; extra == "test"
Provides-Extra: dev
Requires-Dist: transcribe-me[test]; extra == "dev"
Requires-Dist: black>=23.0.0; extra == "dev"
Requires-Dist: isort>=5.0.0; extra == "dev"
Requires-Dist: mypy>=1.0.0; extra == "dev"
Requires-Dist: flake8>=6.0.0; extra == "dev"
Requires-Dist: pre-commit>=3.0.0; extra == "dev"
Dynamic: license-file
